mozilla_location_python-0.5.1.dist-info/DESCRIPTION.rst
mozilla_location_python-0.5.1.dist-info/METADATA
mozilla_location_python-0.5.1.dist-info/RECORD
mozilla_location_python-0.5.1.dist-info/WHEEL
mozilla_location_python-0.5.1.dist-info/metadata.json
mozilla_location_python-0.5.1.dist-info/top_level.txt
mozloc/__init__.py
