Metadata-Version: 2.0
Name: mozilla-location-python
Version: 0.5.1
Summary: Using Mozilla Location services, log location vs. time using WiFi or convert to KML.
Home-page: https://github.com/scivision/mozilla-location-wifi-python
Author: Michael Hirsch, Ph.D.
Author-email: UNKNOWN
License: UNKNOWN
Platform: UNKNOWN
Classifier: Development Status :: 4 - Beta
Classifier: Environment :: Console
Classifier: Intended Audience :: Information Technology
Classifier: Intended Audience :: System Administrators
Classifier: License :: OSI Approved :: MIT License
Classifier: Operating System :: OS Independent
Classifier: Programming Language :: Python :: 3.6
Classifier: Programming Language :: Python :: 3.7
Classifier: Topic :: System :: Networking
Classifier: Topic :: Utilities
Requires-Python: >=3.6
Requires-Dist: pandas
Requires-Dist: requests
Provides-Extra: kml
Requires-Dist: simplekml; extra == 'kml'
Provides-Extra: tests
Requires-Dist: nose; extra == 'tests'
Requires-Dist: coveralls; extra == 'tests'
